README.rst
setup.cfg
setup.py
mining/__init__.py
mining/auth.py
mining/manage.py
mining/multithread.py
mining/settings.py
mining.egg-info/PKG-INFO
mining.egg-info/SOURCES.txt
mining.egg-info/dependency_links.txt
mining.egg-info/not-zip-safe
mining.egg-info/requires.txt
mining.egg-info/top_level.txt
mining/bin/__init__.py
mining/bin/createsuperuser.py
mining/bin/cube.py
mining/bin/scheduler.py
mining/controllers/__init__.py
mining/controllers/export.py
mining/controllers/stream.py
mining/controllers/api/__init__.py
mining/controllers/api/base.py
mining/controllers/api/connection.py
mining/controllers/api/cube.py
mining/controllers/api/dashboard.py
mining/controllers/api/element.py
mining/controllers/api/filter.py
mining/controllers/api/group.py
mining/controllers/api/user.py
mining/controllers/api/widget.py
mining/db/__init__.py
mining/db/datawarehouse.py
mining/db/backends/__init__.py
mining/db/backends/mleveldb.py
mining/db/backends/mredis.py
mining/db/backends/mriak/__init__.py
mining/db/backends/mriak/multiquery.py
mining/test/__init__.py
mining/test/test_db_redis_datawarehouse.py
mining/test/test_mining_utils.py
mining/utils/__init__.py
mining/utils/_pandas.py