Metadata-Version: 1.1
Name: mining
Version: 0.2.0
Summary: BI Application Server written by Python and Riak
Home-page: http://openmining.io
Author: Thiago Avelino <thiago@avelino.xxx>
Author-email: thiago@avelino.xxx
License: MIT License
Download-URL: https://github.com/avelino/mining/tarball/master
Keywords: open mining bi business intelligence platform riak
Platform: UNKNOWN
Classifier: Development Status :: 3 - Alpha
Classifier: Environment :: Web Environment
Classifier: Framework :: Bottle
Classifier: Intended Audience :: Developers
Classifier: License :: OSI Approved :: MIT License
Classifier: Natural Language :: English
Classifier: Operating System :: MacOS :: MacOS X
Classifier: Operating System :: POSIX :: Linux
Classifier: Programming Language :: JavaScript
Classifier: Programming Language :: Python :: 2.7
Classifier: Programming Language :: Python
Classifier: Topic :: Internet :: WWW/HTTP :: Dynamic Content
Classifier: Topic :: Software Development :: Libraries :: Python Modules
Classifier: Topic :: Scientific/Engineering :: Mathematics
Classifier: Topic :: Scientific/Engineering :: Information Analysis
